{"kind":"Notebook","sha256":"562df667159e6a65b45aa8e6b98c6ed34428bd32683a77f0e1ded7f3d7fc95cc","slug":"iter","location":"/chapter8/section2/julia/iter.ipynb","dependencies":[],"frontmatter":{"numbering":{"heading_1":{"enabled":false},"heading_2":{"enabled":false},"heading_3":{"enabled":false},"heading_4":{"enabled":false},"heading_5":{"enabled":false},"heading_6":{"enabled":false}},"kernelspec":{"name":"julia-1.11","display_name":"Julia 1","language":"julia"},"authors":[{"nameParsed":{"literal":"Tobin A. Driscoll","given":"Tobin A.","family":"Driscoll"},"name":"Tobin A. Driscoll","email":"driscoll@udel.edu","id":"contributors-myst-generated-uid-0","corresponding":true},{"nameParsed":{"literal":"Richard J. Braun","given":"Richard J.","family":"Braun"},"name":"Richard J. Braun","id":"contributors-myst-generated-uid-1"}],"github":"https://github.com/fncbook/fnc","math":{"\\float":{"macro":"\\mathbb{F}"},"\\real":{"macro":"\\mathbb{R}"},"\\complex":{"macro":"\\mathbb{C}"},"\\nat":{"macro":"\\mathbb{N}"},"\\integer":{"macro":"\\mathbb{Z}"},"\\rmn":{"macro":"\\mathbb{R}^{#1 \\times #2}"},"\\dd":{"macro":"\\frac{d #1}{d #2}"},"\\ddd":{"macro":"\\frac{d^2 #1}{d #2^2}"},"\\pp":{"macro":"\\frac{\\partial #1}{\\partial #2}"},"\\ppp":{"macro":"\\frac{\\partial^2 #1}{\\partial #2^2}"},"\\ppdd":{"macro":"\\frac{\\partial^2 #1}{\\partial #2 \\partial #3}"},"\\abs":{"macro":"\\left\\lvert #1 \\right\\rvert"},"\\norm":{"macro":"\\left\\lVert #1 \\right\\rVert"},"\\twonorm":{"macro":"\\norm{#1}_2"},"\\onenorm":{"macro":"\\norm{#1}_1"},"\\infnorm":{"macro":"\\norm{#1}_\\infty"},"\\anynorm":{"macro":"\\norm{#1}_#2"},"\\innerprod":{"macro":"\\langle #1,#2 \\rangle"},"\\pr":{"macro":"^{(#1)}"},"\\kron":{"macro":"#1 \\otimes #2"},"\\eye":{"macro":"\\mathbf{e}_#1"},"\\meye":{"macro":"\\mathbf{I}"},"\\Qhat":{"macro":"\\hat{\\mathbf{Q}}"},"\\Rhat":{"macro":"\\hat{\\mathbf{R}}"},"\\bfalpha":{"macro":"\\mathbf{alpha}"},"\\bfdelta":{"macro":"\\mathbf{delta}"},"\\bfzero":{"macro":"\\boldsymbol{0}"},"\\macheps":{"macro":"\\epsilon_\\text{mach}"},"\\fl":{"macro":"\\operatorname{fl}"},"\\diag":{"macro":"\\operatorname{diag}"},"\\ign":{"macro":"\\operatorname{sign}"},"\\Re":{"macro":"\\operatorname{Re}"},"\\Im":{"macro":"\\operatorname{Im}"},"\\ee":{"macro":"\\times 10^"},"\\lnorm":{"macro":"\\|"},"\\rnorm":{"macro":"\\|"},"\\floor":{"macro":"\\lfloor#1\\rfloor"},"\\cI":{"macro":"\\mathcal{I}"},"\\mtx":{"macro":"\\operatorname{mtx}"},"\\myvec":{"macro":"\\operatorname{vec}"},"\\argmin":{"macro":"\\operatorname{argmin}"}},"abbreviations":{"IVP":"initial-value problem","BVP":"boundary-value problem","ONC":"matrix with orthonormal columns","SVD":"singular value decomposition","EVD":"eigenvalue decomposition","SPD":"symmetric positive definite","HPD":"hermitian positive definite","PDE":"partial differential equation","ODE":"ordinary differential equation"},"exports":[{"format":"ipynb","filename":"iter.ipynb","url":"/fnc/build/iter-ec548c26e773a9358422719dac6a1637.ipynb"}]},"widgets":{},"mdast":{"type":"root","children":[{"type":"block","kind":"notebook-content","data":{},"children":[{"type":"paragraph","position":{"start":{"line":1,"column":1},"end":{"line":1,"column":1}},"children":[{"type":"crossReference","position":{"start":{"line":1,"column":1},"end":{"line":1,"column":1}},"children":[{"type":"strong","position":{"start":{"line":1,"column":1},"end":{"line":1,"column":1}},"children":[{"type":"text","value":"Demo ","key":"mzeFtUBIak"},{"type":"text","value":"8.2.2","key":"q1Ig4sVKn3"}],"key":"BJZhPROXaw"}],"identifier":"demo-power-iter","label":"demo-power-iter","kind":"proof:example","template":"Example %s","enumerator":"8.2.2","resolved":true,"html_id":"demo-power-iter","remote":true,"url":"/power","dataUrl":"/power.json","key":"WSCTiY07ug"}],"key":"A2coWC3HBD"},{"type":"paragraph","position":{"start":{"line":3,"column":1},"end":{"line":3,"column":1}},"children":[{"type":"text","value":"We will experiment with the power iteration on a 5×5 matrix with prescribed eigenvalues and dominant eigenvalue at 1.","position":{"start":{"line":3,"column":1},"end":{"line":3,"column":1}},"key":"BZBzwAVsPm"}],"key":"RVuI9yFLDn"}],"key":"aXQCFGaMbx"},{"type":"block","kind":"notebook-code","data":{"execution":{"iopub.status.idle":"2025-01-14T16:39:17.166000Z","iopub.status.busy":"2025-01-14T16:39:11.376000Z","iopub.execute_input":"2025-01-14T16:39:12.635000Z","shell.execute_reply":"2025-01-14T16:39:17.158000Z"}},"children":[{"type":"code","lang":"julia","executable":true,"value":"λ = [1, -0.75, 0.6, -0.4, 0]\n# Make a triangular matrix with eigenvalues on the diagonal.\nA = triu(ones(5, 5), 1) + diagm(λ)","key":"beF3ZwrtTz"},{"type":"output","id":"vGy6CUPN-B_np4ORjdCIA","data":[{"output_type":"execute_result","execution_count":2,"metadata":{},"data":{"text/plain":{"content":"5×5 Matrix{Float64}:\n 1.0   1.0   1.0   1.0  1.0\n 0.0  -0.75  1.0   1.0  1.0\n 0.0   0.0   0.6   1.0  1.0\n 0.0   0.0   0.0  -0.4  1.0\n 0.0   0.0   0.0   0.0  0.0","content_type":"text/plain"}}}],"key":"Q79ohEwTUv"}],"key":"hAGC7iAUm8"},{"type":"block","kind":"notebook-content","data":{},"children":[{"type":"paragraph","position":{"start":{"line":1,"column":1},"end":{"line":1,"column":1}},"children":[{"type":"text","value":"We run the power iteration 60 times. The best estimate of the dominant eigenvalue is the last entry of the first output.","position":{"start":{"line":1,"column":1},"end":{"line":1,"column":1}},"key":"a47bC7015D"}],"key":"yY5Ax41WCS"}],"key":"fhVstzkBiu"},{"type":"block","kind":"notebook-code","data":{"execution":{"iopub.status.idle":"2025-01-14T16:39:17.692000Z","iopub.status.busy":"2025-01-14T16:39:17.221000Z","iopub.execute_input":"2025-01-14T16:39:17.228000Z","shell.execute_reply":"2025-01-14T16:39:17.690000Z"}},"children":[{"type":"code","lang":"julia","executable":true,"value":"β, x = FNC.poweriter(A, 60)\neigval = β[end]","key":"V8TKilszSG"},{"type":"output","id":"nh0sSUxU7pA0Mf7hkctpw","data":[{"output_type":"execute_result","execution_count":3,"metadata":{},"data":{"text/plain":{"content":"1.0000000133244842","content_type":"text/plain"}}}],"key":"OkqBE5NY1h"}],"key":"WpsH4xGosx"},{"type":"block","kind":"notebook-content","data":{},"children":[{"type":"paragraph","position":{"start":{"line":1,"column":1},"end":{"line":1,"column":1}},"children":[{"type":"text","value":"We check for linear convergence using a log-linear plot of the error.","position":{"start":{"line":1,"column":1},"end":{"line":1,"column":1}},"key":"OXQ9HhtKaU"}],"key":"t9T2CyQDQn"}],"key":"ISgZRvqmp2"},{"type":"block","kind":"notebook-code","data":{"execution":{"iopub.status.idle":"2025-01-14T16:39:28.066000Z","iopub.status.busy":"2025-01-14T16:39:17.704000Z","iopub.execute_input":"2025-01-14T16:39:17.704000Z","shell.execute_reply":"2025-01-14T16:39:28.066000Z"}},"children":[{"type":"code","lang":"julia","executable":true,"value":"err = @. 1 - β\nplot(0:59, abs.(err); m=:o, \n    xlabel=L\"k\",  \n    yaxis=(L\"|\\lambda_1-\\beta_k|\", :log10, [1e-10, 1]),\n    title=\"Convergence of power iteration\")","key":"DTqPiISajN"},{"type":"output","id":"kzaaloUxj2Aq3KXW__qRK","data":[{"output_type":"execute_result","execution_count":4,"metadata":{},"data":{"image/png":{"content_type":"image/png","hash":"6e8310a43af2bb76cbd5760da69f1079","path":"/fnc/build/6e8310a43af2bb76cbd5760da69f1079.png"},"text/html":{"content_type":"text/html","hash":"89a966af2f4870ad1396c85c9b9b1c49","path":"/fnc/build/89a966af2f4870ad1396c85c9b9b1c49.html"},"image/svg+xml":{"content_type":"image/svg+xml","hash":"6c8b644dddc054585fd0b771fae640a3","path":"/fnc/build/6c8b644dddc054585fd0b771fae640a3.svg"}}}],"key":"tQka8sf8af"}],"key":"LNLTRwQQwf"},{"type":"block","kind":"notebook-content","data":{},"children":[{"type":"paragraph","position":{"start":{"line":1,"column":1},"end":{"line":1,"column":1}},"children":[{"type":"text","value":"The asymptotic trend seems to be a straight line, consistent with linear convergence. To estimate the convergence rate, we look at the ratio of two consecutive errors in the linear part of the convergence curve. The ratio of the first two eigenvalues should match the observed rate.","position":{"start":{"line":1,"column":1},"end":{"line":1,"column":1}},"key":"rTsctcczbt"}],"key":"KGyAj4CRN7"}],"key":"kOfcfTlSca"},{"type":"block","kind":"notebook-code","data":{"execution":{"iopub.status.idle":"2025-01-14T16:39:29.300000Z","iopub.status.busy":"2025-01-14T16:39:28.083000Z","iopub.execute_input":"2025-01-14T16:39:28.084000Z","shell.execute_reply":"2025-01-14T16:39:29.300000Z"}},"children":[{"type":"code","lang":"julia","executable":true,"value":"@show theory = λ[2] / λ[1];\n@show observed = err[40] / err[39];","key":"pvtMe8Fh86"},{"type":"output","id":"XGwaaMQ_j68QVzjImFvig","data":[{"name":"stdout","output_type":"stream","text":"theory = λ[2] / λ[1] = -0.75"},{"name":"stdout","output_type":"stream","text":"\nobserved = err[40] / err[39] = -0.7501958338312181\n"}],"key":"VbgTjMLJGR"}],"key":"OtP0Lhhoa8"},{"type":"block","kind":"notebook-content","data":{},"children":[{"type":"paragraph","position":{"start":{"line":1,"column":1},"end":{"line":1,"column":1}},"children":[{"type":"text","value":"Note that the error is supposed to change sign on each iteration. The effect of these alternating signs is that estimates oscillate around the exact value.","position":{"start":{"line":1,"column":1},"end":{"line":1,"column":1}},"key":"TayPQaN6YO"}],"key":"OFrakSLGD7"}],"key":"M3ZOewpGPQ"},{"type":"block","kind":"notebook-code","data":{"execution":{"iopub.status.idle":"2025-01-14T16:39:29.654000Z","iopub.status.busy":"2025-01-14T16:39:29.305000Z","iopub.execute_input":"2025-01-14T16:39:29.306000Z","shell.execute_reply":"2025-01-14T16:39:29.652000Z"}},"children":[{"type":"code","lang":"julia","executable":true,"value":"β[26:30]","key":"YnlONkGITI"},{"type":"output","id":"iPIHlGHkVlrv__6OoqIQP","data":[{"output_type":"execute_result","execution_count":6,"metadata":{},"data":{"text/plain":{"content":"5-element Vector{Float64}:\n 1.0002364535428498\n 0.9998235235523728\n 1.0001328738568553\n 0.9999006537033198\n 1.0000746946568222","content_type":"text/plain"}}}],"key":"H07JH7RckV"}],"key":"PACs3hhJUt"},{"type":"block","kind":"notebook-content","data":{},"children":[{"type":"paragraph","position":{"start":{"line":1,"column":1},"end":{"line":1,"column":1}},"children":[{"type":"text","value":"In practical situations, we don’t know the exact eigenvalue that the algorithm is supposed to find. In that case we would base errors on the final ","position":{"start":{"line":1,"column":1},"end":{"line":1,"column":1}},"key":"t4p5g8wKyh"},{"type":"text","value":"β","position":{"start":{"line":1,"column":1},"end":{"line":1,"column":1}},"key":"aUNUvjcYGO"},{"type":"text","value":" that was found, as in the following plot.","position":{"start":{"line":1,"column":1},"end":{"line":1,"column":1}},"key":"d97IAjRt2d"}],"key":"bj7gFWTNyO"}],"key":"bLMoDRO3XY"},{"type":"block","kind":"notebook-code","data":{"execution":{"iopub.status.idle":"2025-01-14T16:39:31.264000Z","iopub.status.busy":"2025-01-14T16:39:29.659000Z","iopub.execute_input":"2025-01-14T16:39:29.659000Z","shell.execute_reply":"2025-01-14T16:39:31.263000Z"}},"children":[{"type":"code","lang":"julia","executable":true,"value":"err = @. β[end] - β[1:end-1]\nplot(0:58, abs.(err), m=:o, \n    xlabel=L\"k\", \n    yaxis=(L\"|\\beta_{60}-\\beta_k|\", :log10, [1e-10, 1]),\n    title=\"Convergence of power iteration\")","key":"QIlYaLbf8q"},{"type":"output","id":"1lKxd8qew8QtOhyNvug1O","data":[{"output_type":"execute_result","execution_count":7,"metadata":{},"data":{"image/png":{"content_type":"image/png","hash":"f4a140fbab1d4feea64851359b8543f9","path":"/fnc/build/f4a140fbab1d4feea64851359b8543f9.png"},"text/html":{"content_type":"text/html","hash":"b339348c58819ce555ec80425feae974","path":"/fnc/build/b339348c58819ce555ec80425feae974.html"},"image/svg+xml":{"content_type":"image/svg+xml","hash":"ea99ea370fcb37d9bfc38367f1582f58","path":"/fnc/build/ea99ea370fcb37d9bfc38367f1582f58.svg"}}}],"key":"bDWGngfom4"}],"key":"Fd50eNTQI2"},{"type":"block","kind":"notebook-content","data":{},"children":[{"type":"paragraph","position":{"start":{"line":1,"column":1},"end":{"line":1,"column":1}},"children":[{"type":"text","value":"The results are very similar until the last few iterations, when the limited accuracy of the reference value begins to show. That is, while it is a good estimate of ","position":{"start":{"line":1,"column":1},"end":{"line":1,"column":1}},"key":"cuZZK6CQDn"},{"type":"inlineMath","value":"\\lambda_1","position":{"start":{"line":1,"column":1},"end":{"line":1,"column":1}},"html":"<span class=\"katex\"><span class=\"katex-mathml\"><math xmlns=\"http://www.w3.org/1998/Math/MathML\"><semantics><mrow><msub><mi>λ</mi><mn>1</mn></msub></mrow><annotation encoding=\"application/x-tex\">\\lambda_1</annotation></semantics></math></span><span class=\"katex-html\" aria-hidden=\"true\"><span class=\"base\"><span class=\"strut\" style=\"height:0.8444em;vertical-align:-0.15em;\"></span><span class=\"mord\"><span class=\"mord mathnormal\">λ</span><span class=\"msupsub\"><span class=\"vlist-t vlist-t2\"><span class=\"vlist-r\"><span class=\"vlist\" style=\"height:0.3011em;\"><span style=\"top:-2.55em;margin-left:0em;margin-right:0.05em;\"><span class=\"pstrut\" style=\"height:2.7em;\"></span><span class=\"sizing reset-size6 size3 mtight\"><span class=\"mord mtight\">1</span></span></span></span><span class=\"vlist-s\">​</span></span><span class=\"vlist-r\"><span class=\"vlist\" style=\"height:0.15em;\"><span></span></span></span></span></span></span></span></span></span>","key":"TzM0JgkGfO"},{"type":"text","value":", it is less good as an estimate of the error in nearby estimates.","position":{"start":{"line":1,"column":1},"end":{"line":1,"column":1}},"key":"psB2Q3bOlW"}],"key":"z2RP3fXhH9"}],"key":"N9ETgYOYvg"}],"key":"nyMM2LB4qx"},"references":{"cite":{"order":[],"data":{}}},"footer":{"navigation":{"prev":{"title":"One","url":"/one","group":"Chapter 8"},"next":{"title":"Conv","url":"/conv","group":"Chapter 8"}}},"domain":"http://localhost:3000"}