{"kind":"Notebook","sha256":"d33d90c97922ddef30891e1326f61a3d9df81182cabb3fa610ec66f395a1cdca","slug":"sing-1","location":"/chapter6/section5/julia/sing.ipynb","dependencies":[],"frontmatter":{"numbering":{"heading_1":{"enabled":false},"heading_2":{"enabled":false},"heading_3":{"enabled":false},"heading_4":{"enabled":false},"heading_5":{"enabled":false},"heading_6":{"enabled":false}},"kernelspec":{"name":"julia-1.11","display_name":"Julia 1.11.2","language":"julia"},"authors":[{"nameParsed":{"literal":"Tobin A. Driscoll","given":"Tobin A.","family":"Driscoll"},"name":"Tobin A. Driscoll","email":"driscoll@udel.edu","id":"contributors-myst-generated-uid-0","corresponding":true},{"nameParsed":{"literal":"Richard J. Braun","given":"Richard J.","family":"Braun"},"name":"Richard J. Braun","id":"contributors-myst-generated-uid-1"}],"github":"https://github.com/fncbook/fnc","math":{"\\float":{"macro":"\\mathbb{F}"},"\\real":{"macro":"\\mathbb{R}"},"\\complex":{"macro":"\\mathbb{C}"},"\\nat":{"macro":"\\mathbb{N}"},"\\integer":{"macro":"\\mathbb{Z}"},"\\rmn":{"macro":"\\mathbb{R}^{#1 \\times #2}"},"\\dd":{"macro":"\\frac{d #1}{d #2}"},"\\ddd":{"macro":"\\frac{d^2 #1}{d #2^2}"},"\\pp":{"macro":"\\frac{\\partial #1}{\\partial #2}"},"\\ppp":{"macro":"\\frac{\\partial^2 #1}{\\partial #2^2}"},"\\ppdd":{"macro":"\\frac{\\partial^2 #1}{\\partial #2 \\partial #3}"},"\\abs":{"macro":"\\left\\lvert #1 \\right\\rvert"},"\\norm":{"macro":"\\left\\lVert #1 \\right\\rVert"},"\\twonorm":{"macro":"\\norm{#1}_2"},"\\onenorm":{"macro":"\\norm{#1}_1"},"\\infnorm":{"macro":"\\norm{#1}_\\infty"},"\\anynorm":{"macro":"\\norm{#1}_#2"},"\\innerprod":{"macro":"\\langle #1,#2 \\rangle"},"\\pr":{"macro":"^{(#1)}"},"\\kron":{"macro":"#1 \\otimes #2"},"\\eye":{"macro":"\\mathbf{e}_#1"},"\\meye":{"macro":"\\mathbf{I}"},"\\Qhat":{"macro":"\\hat{\\mathbf{Q}}"},"\\Rhat":{"macro":"\\hat{\\mathbf{R}}"},"\\bfalpha":{"macro":"\\mathbf{alpha}"},"\\bfdelta":{"macro":"\\mathbf{delta}"},"\\bfzero":{"macro":"\\boldsymbol{0}"},"\\macheps":{"macro":"\\epsilon_\\text{mach}"},"\\fl":{"macro":"\\operatorname{fl}"},"\\diag":{"macro":"\\operatorname{diag}"},"\\ign":{"macro":"\\operatorname{sign}"},"\\Re":{"macro":"\\operatorname{Re}"},"\\Im":{"macro":"\\operatorname{Im}"},"\\ee":{"macro":"\\times 10^"},"\\lnorm":{"macro":"\\|"},"\\rnorm":{"macro":"\\|"},"\\floor":{"macro":"\\lfloor#1\\rfloor"},"\\cI":{"macro":"\\mathcal{I}"},"\\mtx":{"macro":"\\operatorname{mtx}"},"\\myvec":{"macro":"\\operatorname{vec}"},"\\argmin":{"macro":"\\operatorname{argmin}"}},"abbreviations":{"IVP":"initial-value problem","BVP":"boundary-value problem","ONC":"matrix with orthonormal columns","SVD":"singular value decomposition","EVD":"eigenvalue decomposition","SPD":"symmetric positive definite","HPD":"hermitian positive definite","PDE":"partial differential equation","ODE":"ordinary differential equation"},"exports":[{"format":"ipynb","filename":"sing.ipynb","url":"/build/sing-e4f66530624ee3e9c7b5dbe8295ffaa8.ipynb"}]},"widgets":{},"mdast":{"type":"root","children":[{"type":"block","kind":"notebook-content","data":{},"children":[{"type":"paragraph","position":{"start":{"line":1,"column":1},"end":{"line":1,"column":1}},"children":[{"type":"crossReference","position":{"start":{"line":1,"column":1},"end":{"line":1,"column":1}},"children":[{"type":"strong","position":{"start":{"line":1,"column":1},"end":{"line":1,"column":1}},"children":[{"type":"text","value":"Demo ","key":"YKuFRsjFvZ"},{"type":"text","value":"6.5.2","key":"rr6W7yjVlW"}],"key":"yzbhnOo9aH"}],"identifier":"demo-adapt-sing","label":"demo-adapt-sing","kind":"proof:example","template":"Example %s","enumerator":"6.5.2","resolved":true,"html_id":"demo-adapt-sing","remote":true,"url":"/adaptive-rk","dataUrl":"/adaptive-rk.json","key":"vrLA2fry0I"}],"key":"Y3vVS94eg5"},{"type":"paragraph","position":{"start":{"line":3,"column":1},"end":{"line":3,"column":1}},"children":[{"type":"text","value":"In ","position":{"start":{"line":3,"column":1},"end":{"line":3,"column":1}},"key":"J3798rq8CE"},{"type":"crossReference","kind":"proof:example","identifier":"demo-basics-sing","label":"demo-basics-sing","children":[{"type":"text","value":"Demo ","key":"gjAZS4LSir"},{"type":"text","value":"6.1.3","key":"tDYFrmhV6n"}],"template":"Example %s","enumerator":"6.1.3","resolved":true,"html_id":"demo-basics-sing","remote":true,"url":"/basics","dataUrl":"/basics.json","key":"RiP1rqwtHA"},{"type":"text","value":" we saw an ","key":"a02nWQaAId"},{"type":"abbreviation","title":"initial-value problem","children":[{"type":"text","value":"IVP","key":"QDbVkLRzF5"}],"key":"T8Zd3gqU28"},{"type":"text","value":" that appears to blow up in a finite amount of time. Because the solution increases so rapidly as it approaches the blowup, adaptive stepping is required even to get close.","key":"XkEzAyibKM"}],"key":"sfDPoRt1Io"}],"key":"UvaE850b7X"},{"type":"block","kind":"notebook-code","data":{"execution":{"iopub.status.idle":"2025-01-14T16:08:13.412000Z","iopub.status.busy":"2025-01-14T16:07:52.640000Z","iopub.execute_input":"2025-01-14T16:07:55.481000Z","shell.execute_reply":"2025-01-14T16:08:13.406000Z"}},"children":[{"type":"code","lang":"julia","executable":true,"value":"using OrdinaryDiffEq\nf(u, p, t) = (t + u)^2\nivp = ODEProblem(f, 1, (0.0, 1.0))\nt, u = FNC.rk23(ivp, 1e-5);","key":"DkJ50AiLfb"},{"type":"output","id":"xaunXyBVdDWkGL2QPK-MD","data":[{"name":"stderr","output_type":"stream","text":"\u001b[33m\u001b[1m┌ \u001b[22m\u001b[39m\u001b[33m\u001b[1mWarning: \u001b[22m\u001b[39mStepsize too small near t=0.7854087204072808\n\u001b[33m\u001b[1m└ \u001b[22m\u001b[39m\u001b[90m@ FNCFunctions ~/Documents/GitHub/FNCFunctions.jl/src/chapter06.jl:102\u001b[39m\n"}],"key":"foRk9Yn2iy"}],"key":"S5jDo1JiBE"},{"type":"block","kind":"notebook-content","data":{},"children":[{"type":"paragraph","position":{"start":{"line":1,"column":1},"end":{"line":1,"column":1}},"children":[{"type":"text","value":"In fact, the failure of the adaptivity gives a decent idea of when the singularity occurs.","position":{"start":{"line":1,"column":1},"end":{"line":1,"column":1}},"key":"B1wuv4cExd"}],"key":"Rqyqsu1UNK"}],"key":"OjROsqFxfs"},{"type":"block","kind":"notebook-code","data":{"execution":{"iopub.status.idle":"2025-01-14T16:09:03.715000Z","iopub.status.busy":"2025-01-14T16:08:13.462000Z","iopub.execute_input":"2025-01-14T16:08:13.463000Z","shell.execute_reply":"2025-01-14T16:09:03.713000Z"}},"children":[{"type":"code","lang":"julia","executable":true,"value":"plot(t, u;\n    legend=:none,\n    xlabel=L\"t\",  yaxis=(:log10, L\"u(t)\"), \n    title=\"Finite-time blowup\")\n\ntf = t[end]\nvline!([tf], l=:dash)\nannotate!(tf, 1e5, latexstring(@sprintf(\"t = %.6f \", tf)), :right)","key":"D62BRk43bH"},{"type":"output","id":"3FF_TcC1CE76Q3IGYpgI2","data":[{"output_type":"execute_result","execution_count":3,"metadata":{},"data":{"image/png":{"content_type":"image/png","hash":"79dfa2cf97e3907772dff193a0db65fa","path":"/build/79dfa2cf97e3907772dff193a0db65fa.png"},"text/html":{"content_type":"text/html","hash":"1fed8d725c8dbd23c182457bba5b38fd","path":"/build/1fed8d725c8dbd23c182457bba5b38fd.html"},"image/svg+xml":{"content_type":"image/svg+xml","hash":"d0609a756a2723d01abf337b1dc969ff","path":"/build/d0609a756a2723d01abf337b1dc969ff.svg"}}}],"key":"yRD6BAKllb"}],"key":"k6EgXPiuGK"}],"key":"DsM2UbMICX"},"references":{"cite":{"order":[],"data":{}}},"footer":{"navigation":{"prev":{"title":"Basic","url":"/basic","group":"Chapter 6"},"next":{"title":"Ab4","url":"/ab4","group":"Chapter 6"}}},"domain":"http://localhost:3000"}