{"kind":"Notebook","sha256":"fb5f92d99dd203d6ed13dd134a4501f8514e7ad80bdae86079d7a46d5d084d75","slug":"trap-1","location":"/chapter5/section6/matlab/trap.ipynb","dependencies":[],"frontmatter":{"numbering":{"heading_1":{"enabled":false},"heading_2":{"enabled":false},"heading_3":{"enabled":false},"heading_4":{"enabled":false},"heading_5":{"enabled":false},"heading_6":{"enabled":false}},"kernelspec":{"name":"jupyter_matlab_kernel","display_name":"MATLAB Kernel","language":"matlab"},"authors":[{"nameParsed":{"literal":"Tobin A. Driscoll","given":"Tobin A.","family":"Driscoll"},"name":"Tobin A. Driscoll","email":"driscoll@udel.edu","id":"contributors-myst-generated-uid-0","corresponding":true},{"nameParsed":{"literal":"Richard J. Braun","given":"Richard J.","family":"Braun"},"name":"Richard J. Braun","id":"contributors-myst-generated-uid-1"}],"github":"https://github.com/fncbook/fnc","math":{"\\float":{"macro":"\\mathbb{F}"},"\\real":{"macro":"\\mathbb{R}"},"\\complex":{"macro":"\\mathbb{C}"},"\\nat":{"macro":"\\mathbb{N}"},"\\integer":{"macro":"\\mathbb{Z}"},"\\rmn":{"macro":"\\mathbb{R}^{#1 \\times #2}"},"\\dd":{"macro":"\\frac{d #1}{d #2}"},"\\ddd":{"macro":"\\frac{d^2 #1}{d #2^2}"},"\\pp":{"macro":"\\frac{\\partial #1}{\\partial #2}"},"\\ppp":{"macro":"\\frac{\\partial^2 #1}{\\partial #2^2}"},"\\ppdd":{"macro":"\\frac{\\partial^2 #1}{\\partial #2 \\partial #3}"},"\\abs":{"macro":"\\left\\lvert #1 \\right\\rvert"},"\\norm":{"macro":"\\left\\lVert #1 \\right\\rVert"},"\\twonorm":{"macro":"\\norm{#1}_2"},"\\onenorm":{"macro":"\\norm{#1}_1"},"\\infnorm":{"macro":"\\norm{#1}_\\infty"},"\\anynorm":{"macro":"\\norm{#1}_#2"},"\\innerprod":{"macro":"\\langle #1,#2 \\rangle"},"\\pr":{"macro":"^{(#1)}"},"\\kron":{"macro":"#1 \\otimes #2"},"\\eye":{"macro":"\\mathbf{e}_#1"},"\\meye":{"macro":"\\mathbf{I}"},"\\Qhat":{"macro":"\\hat{\\mathbf{Q}}"},"\\Rhat":{"macro":"\\hat{\\mathbf{R}}"},"\\bfalpha":{"macro":"\\mathbf{alpha}"},"\\bfdelta":{"macro":"\\mathbf{delta}"},"\\bfzero":{"macro":"\\boldsymbol{0}"},"\\macheps":{"macro":"\\epsilon_\\text{mach}"},"\\fl":{"macro":"\\operatorname{fl}"},"\\diag":{"macro":"\\operatorname{diag}"},"\\ign":{"macro":"\\operatorname{sign}"},"\\Re":{"macro":"\\operatorname{Re}"},"\\Im":{"macro":"\\operatorname{Im}"},"\\ee":{"macro":"\\times 10^"},"\\lnorm":{"macro":"\\|"},"\\rnorm":{"macro":"\\|"},"\\floor":{"macro":"\\lfloor#1\\rfloor"},"\\cI":{"macro":"\\mathcal{I}"},"\\mtx":{"macro":"\\operatorname{mtx}"},"\\myvec":{"macro":"\\operatorname{vec}"},"\\argmin":{"macro":"\\operatorname{argmin}"}},"abbreviations":{"IVP":"initial-value problem","BVP":"boundary-value problem","ONC":"matrix with orthonormal columns","SVD":"singular value decomposition","EVD":"eigenvalue decomposition","SPD":"symmetric positive definite","HPD":"hermitian positive definite","PDE":"partial differential equation","ODE":"ordinary differential equation"},"exports":[{"format":"ipynb","filename":"trap.ipynb","url":"/fnc/build/trap-6d355210aa18c2b4f44f96070de9acf1.ipynb"}]},"widgets":{},"mdast":{"type":"root","children":[{"type":"block","kind":"notebook-content","data":{},"children":[{"type":"paragraph","position":{"start":{"line":1,"column":1},"end":{"line":1,"column":1}},"children":[{"type":"crossReference","position":{"start":{"line":1,"column":1},"end":{"line":1,"column":1}},"children":[{"type":"strong","position":{"start":{"line":1,"column":1},"end":{"line":1,"column":1}},"children":[{"type":"text","value":"Demo ","key":"Z2fQiRLj7t"},{"type":"text","value":"5.6.2","key":"ryWQhodsFe"}],"key":"r8kFQPSjTC"}],"identifier":"demo-int-trap","label":"demo-int-trap","kind":"proof:example","template":"Example %s","enumerator":"5.6.2","resolved":true,"html_id":"demo-int-trap","remote":true,"url":"/integration","dataUrl":"/integration.json","key":"CFvdz5Pa7S"}],"key":"t30G2FSzHV"},{"type":"paragraph","position":{"start":{"line":3,"column":1},"end":{"line":3,"column":1}},"children":[{"type":"text","value":"We will approximate the integral of the function ","position":{"start":{"line":3,"column":1},"end":{"line":3,"column":1}},"key":"qX9aviUE84"},{"type":"inlineMath","value":"f(x)=e^{\\sin 7x}","position":{"start":{"line":3,"column":1},"end":{"line":3,"column":1}},"html":"<span class=\"katex\"><span class=\"katex-mathml\"><math xmlns=\"http://www.w3.org/1998/Math/MathML\"><semantics><mrow><mi>f</mi><mo stretchy=\"false\">(</mo><mi>x</mi><mo stretchy=\"false\">)</mo><mo>=</mo><msup><mi>e</mi><mrow><mi>sin</mi><mo>⁡</mo><mn>7</mn><mi>x</mi></mrow></msup></mrow><annotation encoding=\"application/x-tex\">f(x)=e^{\\sin 7x}</annotation></semantics></math></span><span class=\"katex-html\" aria-hidden=\"true\"><span class=\"base\"><span class=\"strut\" style=\"height:1em;vertical-align:-0.25em;\"></span><span class=\"mord mathnormal\" style=\"margin-right:0.10764em;\">f</span><span class=\"mopen\">(</span><span class=\"mord mathnormal\">x</span><span class=\"mclose\">)</span><span class=\"mspace\" style=\"margin-right:0.2778em;\"></span><span class=\"mrel\">=</span><span class=\"mspace\" style=\"margin-right:0.2778em;\"></span></span><span class=\"base\"><span class=\"strut\" style=\"height:0.8305em;\"></span><span class=\"mord\"><span class=\"mord mathnormal\">e</span><span class=\"msupsub\"><span class=\"vlist-t\"><span class=\"vlist-r\"><span class=\"vlist\" style=\"height:0.8305em;\"><span style=\"top:-3.063em;margin-right:0.05em;\"><span class=\"pstrut\" style=\"height:2.7em;\"></span><span class=\"sizing reset-size6 size3 mtight\"><span class=\"mord mtight\"><span class=\"mop mtight\"><span class=\"mtight\">s</span><span class=\"mtight\">i</span><span class=\"mtight\">n</span></span><span class=\"mspace mtight\" style=\"margin-right:0.1952em;\"></span><span class=\"mord mtight\">7</span><span class=\"mord mathnormal mtight\">x</span></span></span></span></span></span></span></span></span></span></span></span>","key":"UyP0nuRm5a"},{"type":"text","value":" over the interval ","position":{"start":{"line":3,"column":1},"end":{"line":3,"column":1}},"key":"Es3WvzVIXH"},{"type":"inlineMath","value":"[0,2]","position":{"start":{"line":3,"column":1},"end":{"line":3,"column":1}},"html":"<span class=\"katex\"><span class=\"katex-mathml\"><math xmlns=\"http://www.w3.org/1998/Math/MathML\"><semantics><mrow><mo stretchy=\"false\">[</mo><mn>0</mn><mo separator=\"true\">,</mo><mn>2</mn><mo stretchy=\"false\">]</mo></mrow><annotation encoding=\"application/x-tex\">[0,2]</annotation></semantics></math></span><span class=\"katex-html\" aria-hidden=\"true\"><span class=\"base\"><span class=\"strut\" style=\"height:1em;vertical-align:-0.25em;\"></span><span class=\"mopen\">[</span><span class=\"mord\">0</span><span class=\"mpunct\">,</span><span class=\"mspace\" style=\"margin-right:0.1667em;\"></span><span class=\"mord\">2</span><span class=\"mclose\">]</span></span></span></span>","key":"v5i1ElXudu"},{"type":"text","value":".","position":{"start":{"line":3,"column":1},"end":{"line":3,"column":1}},"key":"rBpyppZ6nF"}],"key":"o9rFGQyz7X"}],"key":"YE4ATzs4mj"},{"type":"block","kind":"notebook-code","data":{},"children":[{"type":"code","lang":"matlab","executable":true,"value":"f = @(x) exp(sin(7 * x));\na = 0;  b = 2;","key":"xZobR73aWc"},{"type":"output","id":"hc2nS-gG_qt7rRgijqHCQ","data":[],"key":"aMWiSc3MvC"}],"key":"Ga3OPa0tV8"},{"type":"block","kind":"notebook-content","data":{},"children":[{"type":"paragraph","position":{"start":{"line":1,"column":1},"end":{"line":1,"column":1}},"children":[{"type":"text","value":"In lieu of the exact value, we use the ","position":{"start":{"line":1,"column":1},"end":{"line":1,"column":1}},"key":"knveIK7ni1"},{"type":"inlineCode","value":"integral","position":{"start":{"line":1,"column":1},"end":{"line":1,"column":1}},"key":"tAWozA8ccg"},{"type":"text","value":" function to find an accurate result.","position":{"start":{"line":1,"column":1},"end":{"line":1,"column":1}},"key":"N7iLFGFBzr"}],"key":"yXPBflWR9p"}],"key":"RuMmkWGTPS"},{"type":"block","kind":"notebook-code","data":{},"children":[{"type":"code","lang":"matlab","executable":true,"value":"I = integral(f, a, b, abstol=1e-14, reltol=1e-14);\nfprintf(\"Integral = %.15f\", I)","key":"iinHyieGyp"},{"type":"output","id":"RSPdLMAs7bHl0GDTrmHeN","data":[{"name":"stdout","output_type":"stream","text":"Integral = 2.663219782761539"}],"key":"YI6GciD0jB"}],"key":"q8AOgv85lp"},{"type":"block","kind":"notebook-content","data":{},"children":[{"type":"paragraph","position":{"start":{"line":1,"column":1},"end":{"line":1,"column":1}},"children":[{"type":"text","value":"Here is the trapezoid result at ","position":{"start":{"line":1,"column":1},"end":{"line":1,"column":1}},"key":"RlRZVBzwqZ"},{"type":"inlineMath","value":"n=40","position":{"start":{"line":1,"column":1},"end":{"line":1,"column":1}},"html":"<span class=\"katex\"><span class=\"katex-mathml\"><math xmlns=\"http://www.w3.org/1998/Math/MathML\"><semantics><mrow><mi>n</mi><mo>=</mo><mn>40</mn></mrow><annotation encoding=\"application/x-tex\">n=40</annotation></semantics></math></span><span class=\"katex-html\" aria-hidden=\"true\"><span class=\"base\"><span class=\"strut\" style=\"height:0.4306em;\"></span><span class=\"mord mathnormal\">n</span><span class=\"mspace\" style=\"margin-right:0.2778em;\"></span><span class=\"mrel\">=</span><span class=\"mspace\" style=\"margin-right:0.2778em;\"></span></span><span class=\"base\"><span class=\"strut\" style=\"height:0.6444em;\"></span><span class=\"mord\">40</span></span></span></span>","key":"tQyB70A0QL"},{"type":"text","value":", and its error.","position":{"start":{"line":1,"column":1},"end":{"line":1,"column":1}},"key":"M1VgAEL18j"}],"key":"YdRv0glPsB"}],"key":"ODNFXeVR1z"},{"type":"block","kind":"notebook-code","data":{},"children":[{"type":"code","lang":"matlab","executable":true,"value":"T = trapezoid(f, a, b, 40);\nfprintf(\"Trapezoid error = %.2e\", I - T)","key":"SyuTVmaXsJ"},{"type":"output","id":"_DqSZE8ceKwfKg33NWeJq","data":[{"name":"stdout","output_type":"stream","text":"Trapezoid error = 9.17e-04"}],"key":"gzOametfjU"}],"key":"SEZs5ABHN4"},{"type":"block","kind":"notebook-content","data":{},"children":[{"type":"paragraph","position":{"start":{"line":1,"column":1},"end":{"line":1,"column":1}},"children":[{"type":"text","value":"In order to check the order of accuracy, we increase ","position":{"start":{"line":1,"column":1},"end":{"line":1,"column":1}},"key":"rSCxTcTH5h"},{"type":"inlineMath","value":"n","position":{"start":{"line":1,"column":1},"end":{"line":1,"column":1}},"html":"<span class=\"katex\"><span class=\"katex-mathml\"><math xmlns=\"http://www.w3.org/1998/Math/MathML\"><semantics><mrow><mi>n</mi></mrow><annotation encoding=\"application/x-tex\">n</annotation></semantics></math></span><span class=\"katex-html\" aria-hidden=\"true\"><span class=\"base\"><span class=\"strut\" style=\"height:0.4306em;\"></span><span class=\"mord mathnormal\">n</span></span></span></span>","key":"X2Xa1clFFv"},{"type":"text","value":" by orders of magnitude and observe how the error decreases.","position":{"start":{"line":1,"column":1},"end":{"line":1,"column":1}},"key":"RED4tFbOcR"}],"key":"oGWZpQmeVB"}],"key":"SwjBxeC3z9"},{"type":"block","kind":"notebook-code","data":{},"children":[{"type":"code","lang":"matlab","executable":true,"value":"n = 10 .^ (1:5)';\nerr = zeros(size(n));\nfor i = 1:length(n)\n    T = trapezoid(f, a, b, n(i));\n    err(i) = I - T;\nend\ndisp(table(n, err, variableNames=[\"n\", \"Trapezoid error\"]))","key":"jWhkFpqRCC"},{"type":"output","id":"AbBuKy8f_k5N_qRTghBdH","data":[{"name":"stdout","output_type":"stream","text":"      n      Trapezoid error\n    _____    _______________\n\n       10        0.012025   \n      100       0.0001473   \n     1000      1.4742e-06   \n    10000      1.4742e-08   \n    1e+05      1.4742e-10   \n\n"}],"key":"xJHd32Mj5V"}],"key":"hJujUUAOm5"},{"type":"block","kind":"notebook-content","data":{},"children":[{"type":"paragraph","position":{"start":{"line":1,"column":1},"end":{"line":1,"column":1}},"children":[{"type":"text","value":"Each increase by a factor of 10 in ","position":{"start":{"line":1,"column":1},"end":{"line":1,"column":1}},"key":"v9UVcggnV5"},{"type":"inlineMath","value":"n","position":{"start":{"line":1,"column":1},"end":{"line":1,"column":1}},"html":"<span class=\"katex\"><span class=\"katex-mathml\"><math xmlns=\"http://www.w3.org/1998/Math/MathML\"><semantics><mrow><mi>n</mi></mrow><annotation encoding=\"application/x-tex\">n</annotation></semantics></math></span><span class=\"katex-html\" aria-hidden=\"true\"><span class=\"base\"><span class=\"strut\" style=\"height:0.4306em;\"></span><span class=\"mord mathnormal\">n</span></span></span></span>","key":"EHDV2w77fh"},{"type":"text","value":" cuts the error by a factor of about 100, which is consistent with second-order convergence. Another check is that a log-log graph should give a line of slope ","position":{"start":{"line":1,"column":1},"end":{"line":1,"column":1}},"key":"EHU9AiJgWi"},{"type":"text","value":"-2","position":{"start":{"line":1,"column":1},"end":{"line":1,"column":1}},"key":"VfJu6pqlRf"},{"type":"text","value":" as ","position":{"start":{"line":1,"column":1},"end":{"line":1,"column":1}},"key":"jSD21droU3"},{"type":"inlineMath","value":"n\\to\\infty","position":{"start":{"line":1,"column":1},"end":{"line":1,"column":1}},"html":"<span class=\"katex\"><span class=\"katex-mathml\"><math xmlns=\"http://www.w3.org/1998/Math/MathML\"><semantics><mrow><mi>n</mi><mo>→</mo><mi mathvariant=\"normal\">∞</mi></mrow><annotation encoding=\"application/x-tex\">n\\to\\infty</annotation></semantics></math></span><span class=\"katex-html\" aria-hidden=\"true\"><span class=\"base\"><span class=\"strut\" style=\"height:0.4306em;\"></span><span class=\"mord mathnormal\">n</span><span class=\"mspace\" style=\"margin-right:0.2778em;\"></span><span class=\"mrel\">→</span><span class=\"mspace\" style=\"margin-right:0.2778em;\"></span></span><span class=\"base\"><span class=\"strut\" style=\"height:0.4306em;\"></span><span class=\"mord\">∞</span></span></span></span>","key":"imRLeTDQe7"},{"type":"text","value":".","position":{"start":{"line":1,"column":1},"end":{"line":1,"column":1}},"key":"rgrCh4GHn0"}],"key":"V3nKYRsYeJ"}],"key":"VcXeewsAUh"},{"type":"block","kind":"notebook-code","data":{},"children":[{"type":"code","lang":"matlab","executable":true,"value":"clf\nloglog(n, abs(err), \"-o\", displayname=\"trapezoid\")\nhold on\nloglog(n, 0.1 * abs(err(end)) * (n / n(end)).^(-2), \"k--\", displayname=\"O(n^{-2})\")\nxlabel(\"n\");  ylabel(\"error\")\ntitle(\"Convergence of trapezoidal integration\")\nlegend();","key":"DFyZfpFLuk"},{"type":"output","id":"3NyrvhdaiKuvKY6E9TfGH","data":[{"output_type":"execute_result","execution_count":15,"metadata":{},"data":{"image/png":{"content_type":"image/png","hash":"6213dfa940c9876a48d8684776aab2b1","path":"/fnc/build/6213dfa940c9876a48d8684776aab2b1.png"}}}],"key":"Ro3X6srNEd"}],"key":"dQvRJNG5Iv"}],"key":"maFIvKjoj8"},"references":{"cite":{"order":[],"data":{}}},"footer":{"navigation":{"prev":{"title":"Round","url":"/round-1","group":"Chapter 5"},"next":{"title":"Extrap","url":"/extrap-1","group":"Chapter 5"}}},"domain":"http://localhost:3000"}